tllab_common/__init__.py
tllab_common/findcells.py
tllab_common/fit.py
tllab_common/io.py
tllab_common/misc.py
tllab_common/pandas_to_polars.py
tllab_common/pytrackmate.py
tllab_common/segmentation.py
tllab_common/trackmate.jy
tllab_common-2026.1.1.dist-info/METADATA
tllab_common-2026.1.1.dist-info/WHEEL
tllab_common-2026.1.1.dist-info/licenses/LICENSE
tllab_common-2026.1.1.dist-info/RECORD
